sphinx_terminal/__init__.py
sphinx_terminal/_version.py
sphinx_terminal/common.py
sphinx_terminal/directive.py
sphinx_terminal/_static/terminal.css
sphinx_terminal-0.1.1.dist-info/licenses/LICENSE
sphinx_terminal-0.1.1.dist-info/METADATA
sphinx_terminal-0.1.1.dist-info/WHEEL
sphinx_terminal-0.1.1.dist-info/top_level.txt
sphinx_terminal-0.1.1.dist-info/RECORD
