Metadata-Version: 2.4
Name: sphinx-terminal
Version: 0.1.1
Summary: A Sphinx extension for rendering terminal input and output.
License-Expression: GPL-3.0
Requires-Python: >=3.10
License-File: LICENSE
Requires-Dist: docutils>=0.21.2
Requires-Dist: sphinx~=7.0
Dynamic: license-file
